{
  "name": "Supta Kapotasana",
  "english_name": "Reclining Pigeon Pose",
  "description": "A supine hip opener that stretches the glutes and piriformis while relieving tension in the hips.",
  "benefits": [
    "Stretches the glutes and piriformis",
    "Relieves tension in the hips",
    "Improves flexibility",
    "Calms the mind"
  ],
  "youtube_links": [
    {
      "title": "How to Do Reclining Pigeon Pose (Supta Kapotasana)",
      "url": "https://www.youtube.com/watch?v=0yI0o3K9s5A"
    }
  ]
}
